PyImageEditor/__init__.py
PyImageEditor-0.1.dist-info/METADATA
PyImageEditor-0.1.dist-info/WHEEL
PyImageEditor-0.1.dist-info/top_level.txt
PyImageEditor-0.1.dist-info/RECORD
